{
    "asset": {
        "format": "jpeg",
        "id": "1662c7c184c3cc407308bcce30ddefef",
        "name": "xxx_xxx_EG946PQ_xxx(16).jpeg",
        "path": "file:C:/Users/Thomas/Desktop/Cours%20ing%C3%A9nieur/Projet%20de%20semestre/photos/testset/xxx_xxx_EG946PQ_xxx(16).jpeg",
        "size": {
            "width": 1920,
            "height": 1280
        },
        "state": 2,
        "type": 1
    },
    "regions": [
        {
            "id": "GnfBkgj73",
            "type": "RECTANGLE",
            "tags": [
                "glass"
            ],
            "boundingBox": {
                "height": 226.56187454512371,
                "width": 70.7662463627546,
                "left": 960.9311348205625,
                "top": 761.0480633642649
            },
            "points": [
                {
                    "x": 960.9311348205625,
                    "y": 761.0480633642649
                },
                {
                    "x": 1031.697381183317,
                    "y": 761.0480633642649
                },
                {
                    "x": 1031.697381183317,
                    "y": 987.6099379093886
                },
                {
                    "x": 960.9311348205625,
                    "y": 987.6099379093886
                }
            ]
        },
        {
            "id": "uEDrJM5j9",
            "type": "RECTANGLE",
            "tags": [
                "glass"
            ],
            "boundingBox": {
                "height": 59.62154294032023,
                "width": 149.72646778006788,
                "left": 369.4742854328322,
                "top": 936.1862888919214
            },
            "points": [
                {
                    "x": 369.4742854328322,
                    "y": 936.1862888919214
                },
                {
                    "x": 519.2007532129,
                    "y": 936.1862888919214
                },
                {
                    "x": 519.2007532129,
                    "y": 995.8078318322416
                },
                {
                    "x": 369.4742854328322,
                    "y": 995.8078318322416
                }
            ]
        },
        {
            "id": "bJrvCOaYX",
            "type": "RECTANGLE",
            "tags": [
                "glass"
            ],
            "boundingBox": {
                "height": 129.67681040756915,
                "width": 154.94085687439377,
                "left": 656.2638669980602,
                "top": 911.592493404294
            },
            "points": [
                {
                    "x": 656.2638669980602,
                    "y": 911.592493404294
                },
                {
                    "x": 811.2047238724539,
                    "y": 911.592493404294
                },
                {
                    "x": 811.2047238724539,
                    "y": 1041.2693038118632
                },
                {
                    "x": 656.2638669980602,
                    "y": 1041.2693038118632
                }
            ]
        },
        {
            "id": "Ahw_cNc6V",
            "type": "RECTANGLE",
            "tags": [
                "glass"
            ],
            "boundingBox": {
                "height": 69.31006641193595,
                "width": 160.90014245877788,
                "left": 750.8671420344325,
                "top": 992.8268001728529
            },
            "points": [
                {
                    "x": 750.8671420344325,
                    "y": 992.8268001728529
                },
                {
                    "x": 911.7672844932105,
                    "y": 992.8268001728529
                },
                {
                    "x": 911.7672844932105,
                    "y": 1062.136866584789
                },
                {
                    "x": 750.8671420344325,
                    "y": 1062.136866584789
                }
            ]
        },
        {
            "id": "5BkrI0kdO",
            "type": "RECTANGLE",
            "tags": [
                "glass"
            ],
            "boundingBox": {
                "height": 91.66814501455605,
                "width": 238.3705140640155,
                "left": 1231.7051861057225,
                "top": 968.9782057405386
            },
            "points": [
                {
                    "x": 1231.7051861057225,
                    "y": 968.9782057405386
                },
                {
                    "x": 1470.075700169738,
                    "y": 968.9782057405386
                },
                {
                    "x": 1470.075700169738,
                    "y": 1060.6463507550945
                },
                {
                    "x": 1231.7051861057225,
                    "y": 1060.6463507550945
                }
            ]
        },
        {
            "id": "djNbeInsO",
            "type": "RECTANGLE",
            "tags": [
                "glass"
            ],
            "boundingBox": {
                "height": 107.31884552401746,
                "width": 61.08242149612027,
                "left": 1054.0446168768185,
                "top": 884.0174388191411
            },
            "points": [
                {
                    "x": 1054.0446168768185,
                    "y": 884.0174388191411
                },
                {
                    "x": 1115.1270383729388,
                    "y": 884.0174388191411
                },
                {
                    "x": 1115.1270383729388,
                    "y": 991.3362843431587
                },
                {
                    "x": 1054.0446168768185,
                    "y": 991.3362843431587
                }
            ]
        },
        {
            "id": "q3sEO13s8",
            "type": "RECTANGLE",
            "tags": [
                "glass"
            ],
            "boundingBox": {
                "height": 184.8268058588064,
                "width": 105.03216688894277,
                "left": 1346.0484738724538,
                "top": 778.9345376182678
            },
            "points": [
                {
                    "x": 1346.0484738724538,
                    "y": 778.9345376182678
                },
                {
                    "x": 1451.0806407613966,
                    "y": 778.9345376182678
                },
                {
                    "x": 1451.0806407613966,
                    "y": 963.7613434770742
                },
                {
                    "x": 1346.0484738724538,
                    "y": 963.7613434770742
                }
            ]
        },
        {
            "id": "M2NNtSmyD",
            "type": "RECTANGLE",
            "tags": [
                "glass"
            ],
            "boundingBox": {
                "height": 120.7337154294032,
                "width": 87.89914979388942,
                "left": 1289.4355449806012,
                "top": 828.122242312591
            },
            "points": [
                {
                    "x": 1289.4355449806012,
                    "y": 828.122242312591
                },
                {
                    "x": 1377.3346947744908,
                    "y": 828.122242312591
                },
                {
                    "x": 1377.3346947744908,
                    "y": 948.8559577419942
                },
                {
                    "x": 1289.4355449806012,
                    "y": 948.8559577419942
                }
            ]
        },
        {
            "id": "46JqFaIlD",
            "type": "RECTANGLE",
            "tags": [
                "glass"
            ],
            "boundingBox": {
                "height": 101.35655476710335,
                "width": 92.36852873423858,
                "left": 1244.7410735935985,
                "top": 844.5182575964337
            },
            "points": [
                {
                    "x": 1244.7410735935985,
                    "y": 844.5182575964337
                },
                {
                    "x": 1337.109602327837,
                    "y": 844.5182575964337
                },
                {
                    "x": 1337.109602327837,
                    "y": 945.8748123635371
                },
                {
                    "x": 1244.7410735935985,
                    "y": 945.8748123635371
                }
            ]
        }
    ],
    "version": "2.2.0"
}