{
    "asset": {
        "format": "jpeg",
        "id": "544708f3619205f17a7b5b66a00dfc00",
        "name": "xxx_xxx_EG946PQ_xxx(382).jpeg",
        "path": "file:C:/Users/Thomas/Desktop/Cours%20ing%C3%A9nieur/Projet%20de%20semestre/photos/testset/xxx_xxx_EG946PQ_xxx(382).jpeg",
        "size": {
            "width": 1920,
            "height": 1280
        },
        "state": 2,
        "type": 1
    },
    "regions": [
        {
            "id": "HBjS7GgFI",
            "type": "RECTANGLE",
            "tags": [
                "glass"
            ],
            "boundingBox": {
                "height": 93.90386189956332,
                "width": 146.00192849781766,
                "left": 443.965071077837,
                "top": 933.9505720069141
            },
            "points": [
                {
                    "x": 443.965071077837,
                    "y": 933.9505720069141
                },
                {
                    "x": 589.9669995756547,
                    "y": 933.9505720069141
                },
                {
                    "x": 589.9669995756547,
                    "y": 1027.8544339064774
                },
                {
                    "x": 443.965071077837,
                    "y": 1027.8544339064774
                }
            ]
        },
        {
            "id": "ldHAIbBUf",
            "type": "RECTANGLE",
            "tags": [
                "glass"
            ],
            "boundingBox": {
                "height": 113.28090884279476,
                "width": 80.45007122938894,
                "left": 974.339498969447,
                "top": 855.6972968977439
            },
            "points": [
                {
                    "x": 974.339498969447,
                    "y": 855.6972968977439
                },
                {
                    "x": 1054.7895701988361,
                    "y": 855.6972968977439
                },
                {
                    "x": 1054.7895701988361,
                    "y": 968.9782057405386
                },
                {
                    "x": 974.339498969447,
                    "y": 968.9782057405386
                }
            ]
        },
        {
            "id": "fzmctz64m",
            "type": "RECTANGLE",
            "tags": [
                "glass"
            ],
            "boundingBox": {
                "height": 84.96076692139738,
                "width": 55.12313591173618,
                "left": 1108.4229131304558,
                "top": 957.0538516648471
            },
            "points": [
                {
                    "x": 1108.4229131304558,
                    "y": 957.0538516648471
                },
                {
                    "x": 1163.546049042192,
                    "y": 957.0538516648471
                },
                {
                    "x": 1163.546049042192,
                    "y": 1042.0146185862445
                },
                {
                    "x": 1108.4229131304558,
                    "y": 1042.0146185862445
                }
            ]
        },
        {
            "id": "Ko5QP6_Yn",
            "type": "RECTANGLE",
            "tags": [
                "glass"
            ],
            "boundingBox": {
                "height": 132.6579557860262,
                "width": 134.82825381910766,
                "left": 963.9108344447138,
                "top": 927.2430801946871
            },
            "points": [
                {
                    "x": 963.9108344447138,
                    "y": 927.2430801946871
                },
                {
                    "x": 1098.7390882638215,
                    "y": 927.2430801946871
                },
                {
                    "x": 1098.7390882638215,
                    "y": 1059.9010359807132
                },
                {
                    "x": 963.9108344447138,
                    "y": 1059.9010359807132
                }
            ]
        }
    ],
    "version": "2.2.0"
}