{
    "asset": {
        "format": "jpeg",
        "id": "60b7fd2437dd0574b73a15615624f160",
        "name": "2018-03-13_07.05.jpeg",
        "path": "file:C:/Users/Thomas/Desktop/Cours%20ing%C3%A9nieur/Projet%20de%20semestre/photos/testset/2018-03-13_07.05.jpeg",
        "size": {
            "width": 1900,
            "height": 1080
        },
        "state": 2,
        "type": 1
    },
    "regions": [
        {
            "id": "gG45LkuMz",
            "type": "RECTANGLE",
            "tags": [
                "wood"
            ],
            "boundingBox": {
                "height": 462.9624235914836,
                "width": 544.7526223213202,
                "left": 311.81379553187134,
                "top": 616.7150170648465
            },
            "points": [
                {
                    "x": 311.81379553187134,
                    "y": 616.7150170648465
                },
                {
                    "x": 856.5664178531916,
                    "y": 616.7150170648465
                },
                {
                    "x": 856.5664178531916,
                    "y": 1079.67744065633
                },
                {
                    "x": 311.81379553187134,
                    "y": 1079.67744065633
                }
            ]
        }
    ],
    "version": "2.2.0"
}