{
    "asset": {
        "format": "jpeg",
        "id": "8679f4e66091fa2f83dec2a1e95e1bd5",
        "name": "2018-04-18_10.38.jpeg",
        "path": "file:C:/Users/Thomas/Desktop/Cours%20ing%C3%A9nieur/Projet%20de%20semestre/photos/testset/2018-04-18_10.38.jpeg",
        "size": {
            "width": 1900,
            "height": 1080
        },
        "state": 2,
        "type": 1
    },
    "regions": [
        {
            "id": "Fu7mz6oiV",
            "type": "RECTANGLE",
            "tags": [
                "bags"
            ],
            "boundingBox": {
                "height": 482.8669504419529,
                "width": 263.8991495570896,
                "left": 494.62662113163793,
                "top": 259.1723549488055
            },
            "points": [
                {
                    "x": 494.62662113163793,
                    "y": 259.1723549488055
                },
                {
                    "x": 758.5257706887276,
                    "y": 259.1723549488055
                },
                {
                    "x": 758.5257706887276,
                    "y": 742.0393053907584
                },
                {
                    "x": 494.62662113163793,
                    "y": 742.0393053907584
                }
            ]
        },
        {
            "id": "Fs7StsUU7",
            "type": "RECTANGLE",
            "tags": [
                "bags"
            ],
            "boundingBox": {
                "height": 561.0102276590497,
                "width": 460.71786223743635,
                "left": 1151.4257776980025,
                "top": 248.11433447098977
            },
            "points": [
                {
                    "x": 1151.4257776980025,
                    "y": 248.11433447098977
                },
                {
                    "x": 1612.1436399354388,
                    "y": 248.11433447098977
                },
                {
                    "x": 1612.1436399354388,
                    "y": 809.1245621300395
                },
                {
                    "x": 1151.4257776980025,
                    "y": 809.1245621300395
                }
            ]
        }
    ],
    "version": "2.2.0"
}