{
    "asset": {
        "format": "jpeg",
        "id": "9afc8daeddc5ba9832d8b2e2af206691",
        "name": "xxx_xxx_EG946PQ_xxx(140).jpeg",
        "path": "file:C:/Users/Thomas/Desktop/Cours%20ing%C3%A9nieur/Projet%20de%20semestre/photos/testset/xxx_xxx_EG946PQ_xxx(140).jpeg",
        "size": {
            "width": 1920,
            "height": 1280
        },
        "state": 2,
        "type": 1
    },
    "regions": [
        {
            "id": "oxdewXFX4",
            "type": "RECTANGLE",
            "tags": [
                "glass"
            ],
            "boundingBox": {
                "height": 76.76275927947599,
                "width": 192.18613603297769,
                "left": 1389.9981056013578,
                "top": 928.7335960243813
            },
            "points": [
                {
                    "x": 1389.9981056013578,
                    "y": 928.7335960243813
                },
                {
                    "x": 1582.1842416343354,
                    "y": 928.7335960243813
                },
                {
                    "x": 1582.1842416343354,
                    "y": 1005.4963553038573
                },
                {
                    "x": 1389.9981056013578,
                    "y": 1005.4963553038573
                }
            ]
        },
        {
            "id": "_Erg1sm8s",
            "type": "RECTANGLE",
            "tags": [
                "glass"
            ],
            "boundingBox": {
                "height": 113.28090884279476,
                "width": 67.04170708050437,
                "left": 1158.3317167798255,
                "top": 963.0160287026929
            },
            "points": [
                {
                    "x": 1158.3317167798255,
                    "y": 963.0160287026929
                },
                {
                    "x": 1225.3734238603297,
                    "y": 963.0160287026929
                },
                {
                    "x": 1225.3734238603297,
                    "y": 1076.2969375454877
                },
                {
                    "x": 1158.3317167798255,
                    "y": 1076.2969375454877
                }
            ]
        },
        {
            "id": "FLRqcAIpN",
            "type": "RECTANGLE",
            "tags": [
                "glass"
            ],
            "boundingBox": {
                "height": 64.09320414847161,
                "width": 121.42000333414161,
                "left": 1130.7701488239572,
                "top": 940.6579501000728
            },
            "points": [
                {
                    "x": 1130.7701488239572,
                    "y": 940.6579501000728
                },
                {
                    "x": 1252.190152158099,
                    "y": 940.6579501000728
                },
                {
                    "x": 1252.190152158099,
                    "y": 1004.7511542485444
                },
                {
                    "x": 1130.7701488239572,
                    "y": 1004.7511542485444
                }
            ]
        },
        {
            "id": "vMCtoU4dq",
            "type": "RECTANGLE",
            "tags": [
                "glass"
            ],
            "boundingBox": {
                "height": 136.3843022197962,
                "width": 84.91956383365664,
                "left": 1061.493695441319,
                "top": 939.9126353256914
            },
            "points": [
                {
                    "x": 1061.493695441319,
                    "y": 939.9126353256914
                },
                {
                    "x": 1146.4132592749756,
                    "y": 939.9126353256914
                },
                {
                    "x": 1146.4132592749756,
                    "y": 1076.2969375454877
                },
                {
                    "x": 1061.493695441319,
                    "y": 1076.2969375454877
                }
            ]
        },
        {
            "id": "Vd9DcTOob",
            "type": "RECTANGLE",
            "tags": [
                "glass"
            ],
            "boundingBox": {
                "height": 46.95198780931587,
                "width": 96.8380213385063,
                "left": 966.8904204049467,
                "top": 977.1760996633916
            },
            "points": [
                {
                    "x": 966.8904204049467,
                    "y": 977.1760996633916
                },
                {
                    "x": 1063.728441743453,
                    "y": 977.1760996633916
                },
                {
                    "x": 1063.728441743453,
                    "y": 1024.1280874727074
                },
                {
                    "x": 966.8904204049467,
                    "y": 1024.1280874727074
                }
            ]
        },
        {
            "id": "AO-eeY66A",
            "type": "RECTANGLE",
            "tags": [
                "glass"
            ],
            "boundingBox": {
                "height": 84.21545214701601,
                "width": 174.3084497757032,
                "left": 268.16682832201747,
                "top": 928.7335960243813
            },
            "points": [
                {
                    "x": 268.16682832201747,
                    "y": 928.7335960243813
                },
                {
                    "x": 442.47527809772066,
                    "y": 928.7335960243813
                },
                {
                    "x": 442.47527809772066,
                    "y": 1012.9490481713974
                },
                {
                    "x": 268.16682832201747,
                    "y": 1012.9490481713974
                }
            ]
        },
        {
            "id": "3YHrVyeV6",
            "type": "RECTANGLE",
            "tags": [
                "glass"
            ],
            "boundingBox": {
                "height": 62.60257459970888,
                "width": 78.21532492725508,
                "left": 553.4665600751697,
                "top": 915.318839838064
            },
            "points": [
                {
                    "x": 553.4665600751697,
                    "y": 915.318839838064
                },
                {
                    "x": 631.6818850024248,
                    "y": 915.318839838064
                },
                {
                    "x": 631.6818850024248,
                    "y": 977.9214144377729
                },
                {
                    "x": 553.4665600751697,
                    "y": 977.9214144377729
                }
            ]
        },
        {
            "id": "7ORsh4bUZ",
            "type": "RECTANGLE",
            "tags": [
                "glass"
            ],
            "boundingBox": {
                "height": 96.13980622270742,
                "width": 95.3482283583899,
                "left": 753.8467279946653,
                "top": 979.4119302674673
            },
            "points": [
                {
                    "x": 753.8467279946653,
                    "y": 979.4119302674673
                },
                {
                    "x": 849.1949563530552,
                    "y": 979.4119302674673
                },
                {
                    "x": 849.1949563530552,
                    "y": 1075.5517364901746
                },
                {
                    "x": 753.8467279946653,
                    "y": 1075.5517364901746
                }
            ]
        }
    ],
    "version": "2.2.0"
}