{
    "asset": {
        "format": "jpeg",
        "id": "c387736705cd69e573d1dd8664612803",
        "name": "xxx_xxx_EG946PQ_xxx(47).jpeg",
        "path": "file:C:/Users/Thomas/Desktop/Cours%20ing%C3%A9nieur/Projet%20de%20semestre/photos/testset/xxx_xxx_EG946PQ_xxx(47).jpeg",
        "size": {
            "width": 1920,
            "height": 1280
        },
        "state": 2,
        "type": 1
    },
    "regions": [
        {
            "id": "5ZT75PysG",
            "type": "RECTANGLE",
            "tags": [
                "glass"
            ],
            "boundingBox": {
                "height": 159.48769559679766,
                "width": 59.59262851600388,
                "left": 636.8962172647914,
                "top": 904.8850015920669
            },
            "points": [
                {
                    "x": 636.8962172647914,
                    "y": 904.8850015920669
                },
                {
                    "x": 696.4888457807954,
                    "y": 904.8850015920669
                },
                {
                    "x": 696.4888457807954,
                    "y": 1064.3726971888645
                },
                {
                    "x": 636.8962172647914,
                    "y": 1064.3726971888645
                }
            ]
        },
        {
            "id": "NxycfKllG",
            "type": "RECTANGLE",
            "tags": [
                "glass"
            ],
            "boundingBox": {
                "height": 76.01744450509462,
                "width": 178.77788554801162,
                "left": 858.8787812196896,
                "top": 942.8937807041484
            },
            "points": [
                {
                    "x": 858.8787812196896,
                    "y": 942.8937807041484
                },
                {
                    "x": 1037.6566667677012,
                    "y": 942.8937807041484
                },
                {
                    "x": 1037.6566667677012,
                    "y": 1018.9112252092431
                },
                {
                    "x": 858.8787812196896,
                    "y": 1018.9112252092431
                }
            ]
        },
        {
            "id": "0Drq-ZNh6",
            "type": "RECTANGLE",
            "tags": [
                "glass"
            ],
            "boundingBox": {
                "height": 63.347889374090244,
                "width": 140.78753940349176,
                "left": 931.8797738845781,
                "top": 888.4891000272926
            },
            "points": [
                {
                    "x": 931.8797738845781,
                    "y": 888.4891000272926
                },
                {
                    "x": 1072.6673132880699,
                    "y": 888.4891000272926
                },
                {
                    "x": 1072.6673132880699,
                    "y": 951.8369894013828
                },
                {
                    "x": 931.8797738845781,
                    "y": 951.8369894013828
                }
            ]
        },
        {
            "id": "ZC9fVd9rk",
            "type": "RECTANGLE",
            "tags": [
                "glass"
            ],
            "boundingBox": {
                "height": 111.04507823871907,
                "width": 159.4103494786615,
                "left": 912.5121241513094,
                "top": 828.8675570869723
            },
            "points": [
                {
                    "x": 912.5121241513094,
                    "y": 828.8675570869723
                },
                {
                    "x": 1071.922473629971,
                    "y": 828.8675570869723
                },
                {
                    "x": 1071.922473629971,
                    "y": 939.9126353256914
                },
                {
                    "x": 912.5121241513094,
                    "y": 939.9126353256914
                }
            ]
        },
        {
            "id": "f4daV_uVq",
            "type": "RECTANGLE",
            "tags": [
                "glass"
            ],
            "boundingBox": {
                "height": 161.72341248180496,
                "width": 55.12313591173618,
                "left": 864.8380668040737,
                "top": 831.103387691048
            },
            "points": [
                {
                    "x": 864.8380668040737,
                    "y": 831.103387691048
                },
                {
                    "x": 919.9612027158098,
                    "y": 831.103387691048
                },
                {
                    "x": 919.9612027158098,
                    "y": 992.8268001728529
                },
                {
                    "x": 864.8380668040737,
                    "y": 992.8268001728529
                }
            ]
        },
        {
            "id": "BxrWElrQF",
            "type": "RECTANGLE",
            "tags": [
                "glass"
            ],
            "boundingBox": {
                "height": 114.02622361717613,
                "width": 77.47037160523763,
                "left": 709.8972099296799,
                "top": 928.7335960243813
            },
            "points": [
                {
                    "x": 709.8972099296799,
                    "y": 928.7335960243813
                },
                {
                    "x": 787.3675815349176,
                    "y": 928.7335960243813
                },
                {
                    "x": 787.3675815349176,
                    "y": 1042.7598196415574
                },
                {
                    "x": 709.8972099296799,
                    "y": 1042.7598196415574
                }
            ]
        },
        {
            "id": "cZSyhmjgf",
            "type": "RECTANGLE",
            "tags": [
                "glass"
            ],
            "boundingBox": {
                "height": 194.51532933042213,
                "width": 127.3792889185257,
                "left": 752.356935014549,
                "top": 848.9898050855168
            },
            "points": [
                {
                    "x": 752.356935014549,
                    "y": 848.9898050855168
                },
                {
                    "x": 879.7362239330746,
                    "y": 848.9898050855168
                },
                {
                    "x": 879.7362239330746,
                    "y": 1043.5051344159388
                },
                {
                    "x": 752.356935014549,
                    "y": 1043.5051344159388
                }
            ]
        },
        {
            "id": "_wPLe4z_W",
            "type": "RECTANGLE",
            "tags": [
                "glass"
            ],
            "boundingBox": {
                "height": 192.27949872634642,
                "width": 67.04170708050437,
                "left": 668.9272778249273,
                "top": 812.4716555221979
            },
            "points": [
                {
                    "x": 668.9272778249273,
                    "y": 812.4716555221979
                },
                {
                    "x": 735.9689849054316,
                    "y": 812.4716555221979
                },
                {
                    "x": 735.9689849054316,
                    "y": 1004.7511542485444
                },
                {
                    "x": 668.9272778249273,
                    "y": 1004.7511542485444
                }
            ]
        },
        {
            "id": "COPm4MjBN",
            "type": "RECTANGLE",
            "tags": [
                "glass"
            ],
            "boundingBox": {
                "height": 140.11064865356622,
                "width": 130.35887487875848,
                "left": 255.8758373241998,
                "top": 882.1542656022563
            },
            "points": [
                {
                    "x": 255.8758373241998,
                    "y": 882.1542656022563
                },
                {
                    "x": 386.2347122029583,
                    "y": 882.1542656022563
                },
                {
                    "x": 386.2347122029583,
                    "y": 1022.2649142558224
                },
                {
                    "x": 255.8758373241998,
                    "y": 1022.2649142558224
                }
            ]
        },
        {
            "id": "yFd2jRXH6",
            "type": "RECTANGLE",
            "tags": [
                "glass"
            ],
            "boundingBox": {
                "height": 129.67692412663754,
                "width": 153.45100706231813,
                "left": 296.473349599903,
                "top": 887.7437852529112
            },
            "points": [
                {
                    "x": 296.473349599903,
                    "y": 887.7437852529112
                },
                {
                    "x": 449.9243566622211,
                    "y": 887.7437852529112
                },
                {
                    "x": 449.9243566622211,
                    "y": 1017.4207093795487
                },
                {
                    "x": 296.473349599903,
                    "y": 1017.4207093795487
                }
            ]
        }
    ],
    "version": "2.2.0"
}