{
    "asset": {
        "format": "jpeg",
        "id": "df792b0bf0c032877c33183ec6d3e002",
        "name": "2018-01-29_10.32.jpeg",
        "path": "file:C:/Users/Thomas/Desktop/Cours%20ing%C3%A9nieur/Projet%20de%20semestre/photos/testset/2018-01-29_10.32.jpeg",
        "size": {
            "width": 1900,
            "height": 1080
        },
        "state": 2,
        "type": 1
    },
    "regions": [
        {
            "id": "3E6s4QyxU",
            "type": "RECTANGLE",
            "tags": [
                "wood"
            ],
            "boundingBox": {
                "height": 361.5574262622192,
                "width": 503.5538094706256,
                "left": 537.6749020668419,
                "top": 352.0332943222884
            },
            "points": [
                {
                    "x": 537.6749020668419,
                    "y": 352.0332943222884
                },
                {
                    "x": 1041.2287115374675,
                    "y": 352.0332943222884
                },
                {
                    "x": 1041.2287115374675,
                    "y": 713.5907205845076
                },
                {
                    "x": 537.6749020668419,
                    "y": 713.5907205845076
                }
            ]
        },
        {
            "id": "C8IgcBA9f",
            "type": "RECTANGLE",
            "tags": [
                "wood"
            ],
            "boundingBox": {
                "height": 303.334475499818,
                "width": 654.404525901059,
                "left": 441.4178022590161,
                "top": 647.4609039865198
            },
            "points": [
                {
                    "x": 441.4178022590161,
                    "y": 647.4609039865198
                },
                {
                    "x": 1095.8223281600751,
                    "y": 647.4609039865198
                },
                {
                    "x": 1095.8223281600751,
                    "y": 950.7953794863379
                },
                {
                    "x": 441.4178022590161,
                    "y": 950.7953794863379
                }
            ]
        },
        {
            "id": "6EC_7Mrpo",
            "type": "RECTANGLE",
            "tags": [
                "wood"
            ],
            "boundingBox": {
                "height": 268.11316669483153,
                "width": 614.8960740895262,
                "left": 449.3194926213227,
                "top": 801.2845422424215
            },
            "points": [
                {
                    "x": 449.3194926213227,
                    "y": 801.2845422424215
                },
                {
                    "x": 1064.2155667108489,
                    "y": 801.2845422424215
                },
                {
                    "x": 1064.2155667108489,
                    "y": 1069.397708937253
                },
                {
                    "x": 449.3194926213227,
                    "y": 1069.397708937253
                }
            ]
        }
    ],
    "version": "2.2.0"
}